nucleotides_to_matrices/__init__.py
nucleotides_to_matrices/cli.py
nucleotides_to_matrices/encodings.py
nucleotides_to_matrices/encodings.txt
nucleotides_to_matrices/nucleotides_to_matrices.py
nucleotides_to_matrices/.ipynb_checkpoints/encodings-checkpoint.txt
nucleotides_to_matrices-0.1.0.dist-info/AUTHORS.rst
nucleotides_to_matrices-0.1.0.dist-info/LICENSE
nucleotides_to_matrices-0.1.0.dist-info/METADATA
nucleotides_to_matrices-0.1.0.dist-info/WHEEL
nucleotides_to_matrices-0.1.0.dist-info/entry_points.txt
nucleotides_to_matrices-0.1.0.dist-info/top_level.txt
nucleotides_to_matrices-0.1.0.dist-info/RECORD
