Metadata-Version: 2.1
Name: nucleotides-to-matrices
Version: 0.1.0
Summary: Utility functions for conversion between IUPAC nucleotide codes and one-hot-like encoded sequence matrices, with extensions for RNA.
Home-page: https://github.com/npdeloss/nucleotides_to_matrices
Author: Nathaniel Delos Santos
Author-email: Nathaniel.P.DelosSantos@jacobs.ucsd.edu
License: MIT license
Keywords: nucleotides_to_matrices
Platform: UNKNOWN
Classifier: Development Status :: 2 - Pre-Alpha
Classifier: Intended Audience :: Developers
Classifier: License :: OSI Approved :: MIT License
Classifier: Natural Language :: English
Classifier: Programming Language :: Python :: 3
Classifier: Programming Language :: Python :: 3.6
Classifier: Programming Language :: Python :: 3.7
Classifier: Programming Language :: Python :: 3.8
Requires-Python: >=3.6
License-File: LICENSE
License-File: AUTHORS.rst
Requires-Dist: Click (>=7.0)
Requires-Dist: numpy (>=1.19.5)
Requires-Dist: pandas (>=1.1.5)
